libraryNrca/__init__.py
libraryNrca/bisextil_year.py
libraryNrca/multplicator_table.py
libraryNrca-0.1.0.dist-info/LICENCE.txt
libraryNrca-0.1.0.dist-info/METADATA
libraryNrca-0.1.0.dist-info/WHEEL
libraryNrca-0.1.0.dist-info/top_level.txt
libraryNrca-0.1.0.dist-info/RECORD
